.bumpversion.cfg
.cookiecutterrc
.coveragerc
.editorconfig
.travis.yml
AUTHORS.rst
CHANGELOG.rst
CONTRIBUTING.rst
LICENSE
MANIFEST.in
README.rst
setup.cfg
setup.py
tox.ini
bin/ne2001_lb
ci/bootstrap.py
ci/templates/.travis.yml
docs/Makefile
docs/authors.rst
docs/changelog.rst
docs/code.rst
docs/conf.py
docs/contributing.rst
docs/index.rst
docs/installation.rst
docs/parameters.rst
docs/readme.rst
docs/requirements.txt
docs/scripts.rst
docs/spelling_wordlist.txt
docs/usage.rst
docs/reference/index.rst
docs/reference/ne2001.rst
src/ne2001/__init__.py
src/ne2001/__main__.py
src/ne2001/cli.py
src/ne2001/density.py
src/ne2001/ne_io.py
src/ne2001/spiral_arms.py
src/ne2001/utils.py
src/ne2001.egg-info/PKG-INFO
src/ne2001.egg-info/SOURCES.txt
src/ne2001.egg-info/dependency_links.txt
src/ne2001.egg-info/entry_points.txt
src/ne2001.egg-info/not-zip-safe
src/ne2001.egg-info/requires.txt
src/ne2001.egg-info/top_level.txt
src/ne2001/data/Convert_data_to_json.ipynb
src/ne2001/data/gal_param.json
src/ne2001/data/model.json
src/ne2001/data/ne2001_params.json
src/ne2001/data/ne_arms_log_mod.inp
src/ne2001/data/ne_gc.inp
src/ne2001/data/ne_gc.json
src/ne2001/data/ne_lism.json
src/ne2001/data/neclumpN.NE2001.dat
src/ne2001/data/nelism.inp
src/ne2001/data/nevoidN.NE2001.dat
src/ne2001/scripts/__init__.py
src/ne2001/scripts/simple_lb.py
tests/test_io.py
tests/test_ne2001.py
tests/test_scripts.py
tests/test_utils.py
tests/profile/profile_ne2001.py